{
  "receipt_id": "X00016469669",
  "source_path": "C:\\Users\\kanis\\Downloads\\AI-OCR dataset-20260428T205037Z-3-001\\AI-OCR dataset\\X00016469669.jpg",
  "fields": {
    "store_name": {
      "value": "tan",
      "confidence": 0.7433,
      "low_confidence": false
    },
    "date": {
      "value": "2019-09-01",
      "confidence": 0.8633,
      "low_confidence": false
    },
    "items": {
      "value": [
        {
          "name": "No.284,JALAN HARMONt 3/",
          "price": 2.0
        }
      ],
      "confidence": 0.8333,
      "low_confidence": false
    },
    "total_amount": {
      "value": 2616.0,
      "confidence": 0.6383,
      "low_confidence": true
    },
    "ocr_mean_confidence": {
      "value": 0.6963,
      "confidence": 0.6963,
      "low_confidence": true
    }
  },
  "raw_text": "tan\nyee\nAIxc ` HO TRAIHNO :\nNo.284,JALAN HARMONt 3/2\nTAMAN DESA HARMONI ,\n81100 Jt OR BAHRU Jt{R\n07-355 2616\nCash Bili\n'0i-143008\nDate\n09/01/2019 8.01;11 PM\nCashier\n01\nDesciiplion\nQty\nPrice\nAmount\nRM\nRM\n15.50\n31.00\nToial\n'31 00\nTolal Amount;\nJIo\nCash Recelved\n701 00\nChange\n70.00\n\"Goods Sold\n0€\nnon-refundablee\nRI#\nThank You\"an\ns*\"Please Come AqaintA+\n3/-00\nchay"
}