{
  "receipt_id": "X51005568889",
  "source_path": "C:\\Users\\kanis\\Downloads\\AI-OCR dataset-20260428T205037Z-3-001\\AI-OCR dataset\\X51005568889.jpg",
  "fields": {
    "store_name": {
      "value": "#ON HWA HARDWARE TRADING",
      "confidence": 0.7387,
      "low_confidence": false
    },
    "date": {
      "value": null,
      "confidence": 0.3537,
      "low_confidence": true
    },
    "items": {
      "value": [
        {
          "name": "NO 37, JALAN MANIS 7_",
          "price": 7.0
        },
        {
          "name": "cash",
          "price": 3.0
        },
        {
          "name": "1,38 TFALUMMNUM ROD",
          "price": 138.0
        },
        {
          "name": "19.60 SR",
          "price": 19.6
        },
        {
          "name": "Goo8e01 ae IOI [etuable/or [etnd C exchange |",
          "price": 1.0
        }
      ],
      "confidence": 0.8287,
      "low_confidence": false
    },
    "total_amount": {
      "value": 9379.0,
      "confidence": 0.6337,
      "low_confidence": true
    },
    "ocr_mean_confidence": {
      "value": 0.686,
      "confidence": 0.686,
      "low_confidence": true
    }
  },
  "raw_text": "#ON HWA HARDWARE TRADING\nCompany Rog; No.\n001056194X\nNO 37, JALAN MANIS 7_\nTAMAN SEGAR,\n66100 CHERAS, KUALA LUmpur;\n+603-9130 2672\nGST\n001 125220352\nTAXINVOICE\nCB::\n09379\n11002p2017 9.35.48 AM\nM\nC1 - 0\nCashier\ncash3\nOy] Descnplon\nPrice\nToleQM;\n1,38 TFALUMMNUM ROD\n5.80\n19.60 SR\n002\n.38\nTYP0:\nTolal\n19.00\nJiscout;\n0.00\nRoundng Ad)\n0.00\nTolal IncUsivo GST:\n19,80\nCASH\n19.60\nSSI Summany\nCodo\nNet Amt\nGST\nTotaRM\nSR\nSR\n18.49\n1.11\n19.00\nTolel\n18.49\n1.11\n19.80\nThank you\n& Please coma again II\nGoo8e01 ae IOI [etuable/or [etnd C exchange |\nRog"
}